<?xml version="1.0" encoding="ISO-8859-1"?>
<proceda>
	<remetente>12345</remetente>
	<destinatario>54321</destinatario>
	<data>100718</data>
	<hora>0714</hora>
	<intercambio>CON50DDMMSSS</intercambio>
    <documentos>
        <sequencia id="0">
	        <documento>CON50DDMMSSS</documento>
	        <transportadora>
				<cnpj>12123123000112</cnpj>
				<razao>TRANSPORTADORA</razao>
			</transportadora>
			<embarcados>
				<filial_emissora>ABCDEF</filial_emissora>
				<serie_conhecimento>ABCDE</serie_conhecimento>
				<numero_conhecimento>ABCDEF</numero_conhecimento>
				<data_emissao>11223333</data_emissao>
				<condicao_frete>C</condicao_frete>
				<cnpj_local>12123123000112</cnpj_local>
				<cnpj_emissor_nf>12123123000121</cnpj_emissor_nf>
				<cnpj_destino_conhecimento_devolucao>12123123000112</cnpj_destino_conhecimento_devolucao>
				<cnpj_destinatario_notas>12123123000112</cnpj_destinatario_notas>
				<cnpj_consignatario>12123123000112</cnpj_consignatario>
				<codigo_fiscal>9999</codigo_fiscal>
				<placa_veiculo>MGABC123</placa_veiculo>
				<numero_romaneio>ABCDEF123456</numero_romaneio>
				<numero_sap1>ABCDEF123456</numero_sap1>
				<numero_sap2>ABCDEF123456</numero_sap2>
				<numero_sap3>ABCDEF123456</numero_sap3>
				<identificacao_autorizacao_carregamento>ABCDEF</identificacao_autorizacao_carregamento>
				<chave_consulta>123456789ABCDE</chave_consulta>
				<protocolo>1123581321</protocolo>
				<codigo_chave_acesso>123456789</codigo_chave_acesso>
				<filial_emissora_conhecimento>ABCDEF</filial_emissora_conhecimento>
				<serie_conhecimento_transportadora>ABCDE</serie_conhecimento_transportadora>
				<numero_conhecimento_transportadora>ABCDEF</numero_conhecimento_transportadora>
				<tipo_transporte>BR08</tipo_transporte>
				<tipo_conhecimento>C</tipo_conhecimento>
				<tipo_frete>1</tipo_frete>
				<acao_documento>I</acao_documento>
				<frete_diferenciado>S</frete_diferenciado>
				<tabela_frete>ABCDEF</tabela_frete>
				<carga_rapida>S</carga_rapida>
				<uf_embarcador>MG</uf_embarcador>
				<uf_emissor>MG</uf_emissor>
				<uf_destinatario>MG</uf_destinatario>
			</embarcados>
			<vlr_conhecimento>
				<qntd_tot_volume>6,2</qntd_tot_volume>
				<peso_bruto>6,3</peso_bruto>
				<peso_cubado>6,4</peso_cubado>
				<peso_densidade>6,4</peso_densidade>
				<valor_frete_total>13,2</valor_frete_total>
				<valor_frete_peso>13,2</valor_frete_peso>
				<frete_valor>13,2</frete_valor>
				<frete_ad_valorem>13,2</frete_ad_valorem>
				<valor_sec>13,2</valor_sec>
				<valor_itr>13,2</valor_itr>
				<valor_despacho>13,2</valor_despacho>
				<valor_pedagio>13,2</valor_pedagio>
				<valor_ademe_gris>13,2</valor_ademe_gris>
				<valor_total_despesa_extra>13,2</valor_total_despesa_extra>
				<valor_desconto_ou_acrescimo>13,2</valor_desconto_ou_acrescimo>
				<indicador_desconto_ou_acrescimo>A</indicador_desconto_ou_acrescimo>
				<base_calculo_apuracao_icms>13,2</base_calculo_apuracao_icms>
				<taxa_icms>1</taxa_icms>
				<valor_icms>13,2</valor_icms>
				<substituicao_tributaria>1</substituicao_tributaria>
				<base_calculo_icms_subst_tributaria>13,2</base_calculo_icms_subst_tributaria>
				<taxa_icms_subst_tributaria>3,2</taxa_icms_subst_tributaria>
				<valor_icms_subst_tributaria>13,2</valor_icms_subst_tributaria>
				<base_calculo_iss>13,2</base_calculo_iss>
				<taxa_iss>3,2</taxa_iss>
				<valor_iss>13,2</valor_iss>
				<valor_ir>13,2</valor_ir>
				<direito_fiscal>Z23</direito_fiscal>
				<tipo_imposto>ICM1</tipo_imposto>
			</vlr_conhecimento>
			<componente_conhecimento>
				<cnpj>12123123000112</cnpj>
				<numero_nf>123456789</numero_nf>
				<serie>123</serie>
				<data_emissao>11223333</data_emissao>
				<valor_nf>13,2</valor_nf>
				<otde_total>6,2</otde_total>
				<peso_bruto>6,3</peso_bruto>
				<peso_densidade>6,4</peso_densidade>
				<peso_cubado>6,4</peso_cubado>
				<identificacao_pedido>ABCDEF123456</identificacao_pedido>
				<numero_romaneio>123456789</numero_romaneio>
				<numero_sap1>123456789</numero_sap1>
				<numero_sap2>123456789</numero_sap2>
				<numero_sap3>123456789</numero_sap3>
				<nf_devolucao>S</nf_devolucao>
				<tipo_nf>1</tipo_nf>
				<indicacao_bonificacao>S</indicacao_bonificacao>
				<cfop>1234</cfop>
				<uf>MG</uf>
				<desdobro>ABCDEF</desdobro>
			</componente_conhecimento>
			<dados_entrega>
				<cnpj1>12123123000112</cnpj1>
				<razao1>TRANSPORTADORA1</razao1>
				<serie1>123</serie1>
				<numero_nf1>123456789</numero_nf1>
				<cnpj2>12123123000112</cnpj2>
				<razao2>TRANSPORTADORA2</razao2>
				<serie2>123</serie2>
				<numero_nf2>123456789</numero_nf2>
				<cnpj3>12123123000112</cnpj3>
				<razao3>TRANSPORTADORA3</razao3>
				<serie3>123</serie3>
				<numero_nf3>123456789</numero_nf3>
				<redespacho_filial_emissora>ABCDEF</redespacho_filial_emissora>
				<redespacho_serie_conhecimento>ABC</redespacho_serie_conhecimento>
				<redespacho_numero_conhecimento>123456789</redespacho_numero_conhecimento>
				<redespacho_cnpj_transportadora>12123123000112</redespacho_cnpj_transportadora>
			</dados_entrega>
			<dados_consignatario>
				<razao>TRANSPORTADORA</razao>
				<cnpj>12123123000112</cnpj>
				<inscricao_estadual>ABCDEF123456</inscricao_estadual>
				<endereco>RUA ABC, 123</endereco>
				<bairro>ABCDEF</bairro>
				<cidade>ABCDEFGH</cidade>
				<codigo_postal>122233344</codigo_postal>
				<codigo_municipio>222222222</codigo_municipio>
				<uf>MG</uf>
				<numero_comunicacao>11922222222</numero_comunicacao>
			</dados_consignatario>
			<final>
				<qntd_total_conhecimentos>999</qntd_total_conhecimentos>
				<valor_total_conhecimentos>13,2</valor_total_conhecimentos>
			</final>
		</sequencia>
    </documentos>
</proceda>